[{"name":"Thị trấn Mậu A","code":"04375"},{"name":"Xã Lang Thíp","code":"04378"},{"name":"Xã Lâm Giang","code":"04381"},{"name":"Xã Châu Quế Thượng","code":"04384"},{"name":"Xã Châu Quế Hạ","code":"04387"},{"name":"Xã An Bình","code":"04390"},{"name":"Xã Quang Minh","code":"04393"},{"name":"Xã Đông An","code":"04396"},{"name":"Xã Đông Cuông","code":"04399"},{"name":"Xã Phong Dụ Hạ","code":"04402"},{"name":"Xã Mậu Đông","code":"04405"},{"name":"Xã Ngòi A","code":"04408"},{"name":"Xã Xuân Tầm","code":"04411"},{"name":"Xã Tân Hợp","code":"04414"},{"name":"Xã An Thịnh","code":"04417"},{"name":"Xã Yên Thái","code":"04420"},{"name":"Xã Phong Dụ Thượng","code":"04423"},{"name":"Xã Yên Hợp","code":"04426"},{"name":"Xã Đại Sơn","code":"04429"},{"name":"Xã Đại Phác","code":"04435"},{"name":"Xã Yên Phú","code":"04438"},{"name":"Xã Xuân Ái","code":"04441"},{"name":"Xã Viễn Sơn","code":"04447"},{"name":"Xã Mỏ Vàng","code":"04450"},{"name":"Xã Nà Hẩu","code":"04453"}]