[{"name":"Thị trấn Hợp Hòa","code":"08869"},{"name":"Xã Hoàng Hoa","code":"08872"},{"name":"Xã Đồng Tĩnh","code":"08875"},{"name":"Xã Kim Long","code":"08878"},{"name":"Xã Hướng Đạo","code":"08881"},{"name":"Xã Đạo Tú","code":"08884"},{"name":"Xã An Hòa","code":"08887"},{"name":"Xã Thanh Vân","code":"08890"},{"name":"Xã Duy Phiên","code":"08893"},{"name":"Xã Hoàng Đan","code":"08896"},{"name":"Xã Hoàng Lâu","code":"08899"},{"name":"Xã Vân Hội","code":"08902"},{"name":"Xã Hợp Thịnh","code":"08905"}]