[{"name":"Thị trấn Tiên Lãng","code":"11755"},{"name":"Xã Đại Thắng","code":"11758"},{"name":"Xã Tiên Cường","code":"11761"},{"name":"Xã Tự Cường","code":"11764"},{"name":"Xã Quyết Tiến","code":"11770"},{"name":"Xã Khởi Nghĩa","code":"11773"},{"name":"Xã Tiên Thanh","code":"11776"},{"name":"Xã Cấp Tiến","code":"11779"},{"name":"Xã Kiến Thiết","code":"11782"},{"name":"Xã Đoàn Lập","code":"11785"},{"name":"Xã Bạch Đằng","code":"11788"},{"name":"Xã Quang Phục","code":"11791"},{"name":"Xã Toàn Thắng","code":"11794"},{"name":"Xã Tiên Thắng","code":"11797"},{"name":"Xã Tiên Minh","code":"11800"},{"name":"Xã Bắc Hưng","code":"11803"},{"name":"Xã Nam Hưng","code":"11806"},{"name":"Xã Hùng Thắng","code":"11809"},{"name":"Xã Tây Hưng","code":"11812"},{"name":"Xã Đông Hưng","code":"11815"},{"name":"Xã Vinh Quang","code":"11821"}]