[{"name":"Thị trấn Tân Kỳ","code":"17266"},{"name":"Xã Tân Hợp","code":"17269"},{"name":"Xã Tân Phú","code":"17272"},{"name":"Xã Tân Xuân","code":"17275"},{"name":"Xã Giai Xuân","code":"17278"},{"name":"Xã Nghĩa Bình","code":"17281"},{"name":"Xã Nghĩa Đồng","code":"17284"},{"name":"Xã Đồng Văn","code":"17287"},{"name":"Xã Nghĩa Thái","code":"17290"},{"name":"Xã Nghĩa Hợp","code":"17293"},{"name":"Xã Nghĩa Hoàn","code":"17296"},{"name":"Xã Nghĩa Phúc","code":"17299"},{"name":"Xã Tiên Kỳ","code":"17302"},{"name":"Xã Tân An","code":"17305"},{"name":"Xã Nghĩa Dũng","code":"17308"},{"name":"Xã Tân Long","code":"17311"},{"name":"Xã Kỳ Sơn","code":"17314"},{"name":"Xã Hương Sơn","code":"17317"},{"name":"Xã Kỳ Tân","code":"17320"},{"name":"Xã Phú Sơn","code":"17323"},{"name":"Xã Tân Hương","code":"17325"},{"name":"Xã Nghĩa Hành","code":"17326"}]