[{"name":"Thị trấn Khánh Vĩnh","code":"22609"},{"name":"Xã Khánh Hiệp","code":"22612"},{"name":"Xã Khánh Bình","code":"22615"},{"name":"Xã Khánh Trung","code":"22618"},{"name":"Xã Khánh Đông","code":"22621"},{"name":"Xã Khánh Thượng","code":"22624"},{"name":"Xã Khánh Nam","code":"22627"},{"name":"Xã Sông Cầu","code":"22630"},{"name":"Xã Giang Ly","code":"22633"},{"name":"Xã Cầu Bà","code":"22636"},{"name":"Xã Liên Sang","code":"22639"},{"name":"Xã Khánh Thành","code":"22642"},{"name":"Xã Khánh Phú","code":"22645"},{"name":"Xã Sơn Thái","code":"22648"}]