[{"name":"Phường 11","code":"29863"},{"name":"Phường 1","code":"29866"},{"name":"Phường 2","code":"29869"},{"name":"Phường 4","code":"29872"},{"name":"Phường 3","code":"29875"},{"name":"Phường 6","code":"29878"},{"name":"Xã Mỹ Ngãi","code":"29881"},{"name":"Xã Mỹ Tân","code":"29884"},{"name":"Xã Mỹ Trà","code":"29887"},{"name":"Phường Mỹ Phú","code":"29888"},{"name":"Xã Tân Thuận Tây","code":"29890"},{"name":"Phường Hoà Thuận","code":"29892"},{"name":"Xã Hòa An","code":"29893"},{"name":"Xã Tân Thuận Đông","code":"29896"},{"name":"Xã Tịnh Thới","code":"29899"}]